[
  {
    "op": "add",
    "path": "/attributesByType/saucepan-burned/simmerRecipes/-",
    "value": {
					"Ingredients": [
						{ "type": "item", "code": "waterportion", "quantity": 20 },
						{ "type": "item", "code": "herbbundle-*", "quantity": 1 }
					],
					"Simmering": {
						"meltingPoint": 100,
						"meltingDuration": 100,
						"smeltedRatio": 1,
						"smeltingType": "bake",
						"smeltedStack": { "type": "item", "code": "expandedfoods:tea-herb", "quantity": 10 },
						"requiresContainer": false
					}
			},
    "file": "blocktypes/saucepan.json",
    dependsOn: [{ "modid": "wildcraft" }]
  },
  {
    "op": "add",
    "path": "/attributesByType/saucepan-burned/simmerRecipes/-",
    "value": {
					"Ingredients": [
						{ "type": "item", "code": "waterportion", "quantity": 20 },
						{ "type": "item", "code": "wildcraft:herbs-*", "quantity": 1 }
					],
					"Simmering": {
						"meltingPoint": 100,
						"meltingDuration": 100,
						"smeltedRatio": 1,
						"smeltingType": "bake",
						"smeltedStack": { "type": "item", "code": "expandedfoods:tea-herb", "quantity": 10  },
						"requiresContainer": false
					}
			},
    "file": "blocktypes/saucepan.json",
    dependsOn: [{ "modid": "wildcraft" }]
  },
]